async_worker_manager/__init__.py
async_worker_manager-1.0.0.dist-info/METADATA
async_worker_manager-1.0.0.dist-info/WHEEL
async_worker_manager-1.0.0.dist-info/RECORD
