Metadata-Version: 2.1
Name: async_worker_manager
Version: 1.0.0
Summary: Asyncio Queues and Workers wrapper
Author: Royi Reshef
Requires-Python: >=3.7,<4.0
Classifier: Programming Language :: Python :: 3
Classifier: Programming Language :: Python :: 3.7
Classifier: Programming Language :: Python :: 3.8
Classifier: Programming Language :: Python :: 3.9
Classifier: Programming Language :: Python :: 3.10
Classifier: Programming Language :: Python :: 3.11
